README.md
setup.py
django_loki/__init__.py
django_loki/formatters.py
django_loki/handlers.py
django_loki.egg-info/PKG-INFO
django_loki.egg-info/SOURCES.txt
django_loki.egg-info/dependency_links.txt
django_loki.egg-info/requires.txt
django_loki.egg-info/top_level.txt