Metadata-Version: 2.1
Name: django-loki
Version: 0.1.4
Summary: logging handler with loki for django
Home-page: https://github.com/zepc007/django-loki
Author: zepc007
Author-email: zepc007@gmail.com
License: MIT
Keywords: python,loki,grafana,logging,metrics
Platform: UNKNOWN
Classifier: License :: OSI Approved :: MIT License
Classifier: Environment :: Web Environment
Classifier: Programming Language :: Python :: 3.6
Classifier: Programming Language :: Python :: 3.7
Classifier: Programming Language :: Python :: 3.8
Classifier: Programming Language :: Python :: 3.9
Classifier: Programming Language :: Python :: 3.10
Classifier: Development Status :: 3 - Alpha 
